pygopherd/GopherExceptions.py
pygopherd/__init__.py
pygopherd/fileext.py
pygopherd/gopherentry.py
pygopherd/initialization.py
pygopherd/logger.py
pygopherd/server.py
pygopherd/sighandlers.py
pygopherd/testutil.py
pygopherd/handlers/HandlerMultiplexer.py
pygopherd/handlers/UMN.py
pygopherd/handlers/ZIP.py
pygopherd/handlers/__init__.py
pygopherd/handlers/base.py
pygopherd/handlers/dir.py
pygopherd/handlers/file.py
pygopherd/handlers/gophermap.py
pygopherd/handlers/html.py
pygopherd/handlers/mbox.py
pygopherd/handlers/pyg.py
pygopherd/handlers/scriptexec.py
pygopherd/handlers/tal.py
pygopherd/handlers/url.py
pygopherd/handlers/virtual.py
pygopherd/protocols/ProtocolMultiplexer.py
pygopherd/protocols/__init__.py
pygopherd/protocols/base.py
pygopherd/protocols/enhanced.py
pygopherd/protocols/gemini.py
pygopherd/protocols/gopherp.py
pygopherd/protocols/http.py
pygopherd/protocols/rfc1436.py
pygopherd/protocols/spartan.py
pygopherd/protocols/wap.py
pygopherd-3.0.1.data/scripts/pygopherd
pygopherd-3.0.1.dist-info/COPYING
pygopherd-3.0.1.dist-info/METADATA
pygopherd-3.0.1.dist-info/WHEEL
pygopherd-3.0.1.dist-info/top_level.txt
pygopherd-3.0.1.dist-info/RECORD
