Metadata-Version: 2.1
Name: pygopherd
Version: 3.0.1
Summary: Multiprotocol Internet Gopher Information Server
Home-page: https://www.github.com/michael-lazar/pygopherd
Author: Michael Lazar
Author-email: lazar.michael22@gmail.com
License: GPLv2
Requires-Python: >=3.7
License-File: COPYING
